django_cv1/__init__.py
django_cv1/admin.py
django_cv1/apps.py
django_cv1/models.py
django_cv1/tests.py
django_cv1/urls.py
django_cv1/views.py
django_cv1/migrations/0001_initial.py
django_cv1/migrations/0002_personne_nom_prenom_alter_personne_adresse_and_more.py
django_cv1/migrations/__init__.py
django_cv1/templates/django_cv1/lookup1.html
django_cv1/templates/django_cv1/moncv.html
django_cv1-0.4.0.dist-info/licenses/LICENCE
django_cv1-0.4.0.dist-info/METADATA
django_cv1-0.4.0.dist-info/WHEEL
django_cv1-0.4.0.dist-info/top_level.txt
django_cv1-0.4.0.dist-info/RECORD
